plotext/__init__.py
plotext/__main__.py
plotext/_build.py
plotext/_core.py
plotext/_date.py
plotext/_default.py
plotext/_dict.py
plotext/_doc.py
plotext/_doc_utils.py
plotext/_figure.py
plotext/_global.py
plotext/_matrix.py
plotext/_monitor.py
plotext/_shtab.py
plotext/_utility.py
plotext/plotext_cli.py
plotext-5.3.2.dist-info/LICENSE
plotext-5.3.2.dist-info/METADATA
plotext-5.3.2.dist-info/WHEEL
plotext-5.3.2.dist-info/entry_points.txt
plotext-5.3.2.dist-info/top_level.txt
plotext-5.3.2.dist-info/RECORD
