Metadata-Version: 2.1
Name: plotext
Version: 5.3.2
Summary: plotext plots directly on terminal
Home-page: https://github.com/piccolomo/plotext
Author: Savino Piccolomo
Author-email: piccolomo@gmail.com
License: MIT
Requires-Python: >=3.5
Provides-Extra: completion
Provides-Extra: image
Provides-Extra: video
License-File: LICENSE
